{
  "asset_id": "authored_sherman_retopo_v1",
  "display_name": "Authored Sherman Retopo V1",
  "generated_at": "2026-07-04T17:23:04.678Z",
  "generator": "scripts/export_authored_sherman_retopo.mjs",
  "output_glb": "public/tftm/models/authored_sherman_retopo_v1/authored_sherman_retopo_v1.glb",
  "source_policy": "fully authored low-poly hard-surface geometry; no Meshy chassis or turret imports",
  "uv_policy": "split face texture plates, one 0-1 rectangular UV material per paintable surface group",
  "dalle_paintability": {
    "template_dir": "assets/authored/authored_sherman_retopo_v1/texture_templates",
    "runtime_plate_dir": "public/tftm/models/authored_sherman_retopo_v1/texture_plates",
    "prompt_rule": "Use the filename/surface id in the prompt; do not ask DALL-E to paint labels or readable typography inside the image.",
    "first_pass": "albedo plates only; derive roughness/normal after cloud/Sense accepts silhouette and paint language."
  },
  "face_plate_ids": [
    "hull_glacis",
    "hull_left",
    "hull_right",
    "hull_rear",
    "engine_deck",
    "turret_front",
    "turret_left",
    "turret_right",
    "turret_top",
    "mantlet",
    "barrel_strip",
    "track_outer",
    "track_inner_top_bottom",
    "wheel_disc",
    "bogie_side"
  ],
  "node_contract": [
    "tank_root",
    "hull_root",
    "turret_traverse_pivot",
    "turret_shell",
    "cannon_elevation_pivot",
    "mantlet_block__mantlet",
    "barrel__barrel_strip",
    "left_track_motion",
    "right_track_motion",
    "left_roadwheel_group",
    "right_roadwheel_group",
    "commander_hatch__turret_top"
  ],
  "runtime_contract": {
    "turret_traverse": "rotate turret_traverse_pivot around Y",
    "cannon_elevation": "rotate cannon_elevation_pivot around local Z/X adapter in runtime as needed",
    "tread_motion": "scroll material maps on left_track_motion and right_track_motion",
    "wheel_motion": "rotate children of left_roadwheel_group and right_roadwheel_group",
    "commander_hatch": "commander_hatch__turret_top is a named posture marker, not final hatch rig"
  },
  "approximate_triangles": 1834
}
